acmturtleoj/__init__.py
acmturtleoj/oj.py
acmturtleoj/svg_turtle.py
acmturtleoj-0.0.3.7.dist-info/LICENSE.txt
acmturtleoj-0.0.3.7.dist-info/METADATA
acmturtleoj-0.0.3.7.dist-info/WHEEL
acmturtleoj-0.0.3.7.dist-info/entry_points.txt
acmturtleoj-0.0.3.7.dist-info/top_level.txt
acmturtleoj-0.0.3.7.dist-info/RECORD
