Metadata-Version: 2.1
Name: acmturtleoj
Version: 0.0.3.7
Summary: A Python OJ client for turtle
Home-page: https://github.com/lifubang/acmturtle
Author: Lifubang
Author-email: lifubang@acmcoder.com
License: UNKNOWN
Project-URL: Bug Reports, https://github.com/pypa/sampleproject/issues
Project-URL: Funding, https://donate.pypi.org
Project-URL: Say Thanks!, http://saythanks.io/to/example
Project-URL: Source, https://github.com/pypa/sampleproject/
Keywords: sample setuptools development
Platform: UNKNOWN
Classifier: Development Status :: 3 - Alpha
Classifier: Intended Audience :: Developers
Classifier: Topic :: Software Development :: Build Tools
Classifier: License :: OSI Approved :: MIT License
Classifier: Programming Language :: Python :: 3
Classifier: Programming Language :: Python :: 3.5
Classifier: Programming Language :: Python :: 3.6
Classifier: Programming Language :: Python :: 3.7
Classifier: Programming Language :: Python :: 3.8
Requires-Python: >=3.5
Requires-Dist: peppercorn
Requires-Dist: svgwrite
Provides-Extra: dev
Requires-Dist: check-manifest ; extra == 'dev'
Provides-Extra: test
Requires-Dist: coverage ; extra == 'test'
